pyaddlicense/__init__.py
pyaddlicense/main.py
pyaddlicense-0.3.0.dist-info/LICENSE
pyaddlicense-0.3.0.dist-info/METADATA
pyaddlicense-0.3.0.dist-info/WHEEL
pyaddlicense-0.3.0.dist-info/entry_points.txt
pyaddlicense-0.3.0.dist-info/RECORD
