Metadata-Version: 2.1
Name: pyaddlicense
Version: 0.3.0
Summary: 
Author: Mikey Coward
Author-email: pyaddlicense@kixa.me
Requires-Python: >=3.7,<4.0
Classifier: Programming Language :: Python :: 3
Classifier: Programming Language :: Python :: 3.7
Classifier: Programming Language :: Python :: 3.8
Classifier: Programming Language :: Python :: 3.9
Classifier: Programming Language :: Python :: 3.10
Classifier: Programming Language :: Python :: 3.11
Requires-Dist: pathspec (>=0.9.0)
Requires-Dist: rich (>=12.0.0)
